CHANGES.rst
MANIFEST.in
README.rst
setup.cfg
setup.py
docs/LICENSE.GPL
docs/LICENSE.txt
zest/__init__.py
zest.emailhider.egg-info/PKG-INFO
zest.emailhider.egg-info/SOURCES.txt
zest.emailhider.egg-info/dependency_links.txt
zest.emailhider.egg-info/entry_points.txt
zest.emailhider.egg-info/namespace_packages.txt
zest.emailhider.egg-info/not-zip-safe
zest.emailhider.egg-info/requires.txt
zest.emailhider.egg-info/top_level.txt
zest/emailhider/__init__.py
zest/emailhider/configure.zcml
zest/emailhider/interfaces.py
zest/emailhider/migration.py
zest/emailhider/profile.zcml
zest/emailhider/rebuild_i18n.sh
zest/emailhider/testing.py
zest/emailhider/browser/__init__.py
zest/emailhider/browser/configure.zcml
zest/emailhider/browser/emailhider.js
zest/emailhider/browser/emailhider.py
zest/emailhider/browser/templates/emailhider.pt
zest/emailhider/browser/templates/test.pt
zest/emailhider/locales/zest.emailhider.pot
zest/emailhider/locales/en/LC_MESSAGES/zest.emailhider.mo
zest/emailhider/locales/en/LC_MESSAGES/zest.emailhider.po
zest/emailhider/locales/nl/LC_MESSAGES/zest.emailhider.mo
zest/emailhider/locales/nl/LC_MESSAGES/zest.emailhider.po
zest/emailhider/profiles/default/browserlayer.xml
zest/emailhider/profiles/default/jsregistry.xml
zest/emailhider/profiles/default/kssregistry.xml
zest/emailhider/profiles/default/metadata.xml
zest/emailhider/tests/__init__.py
zest/emailhider/tests/test_browser.py
zest/emailhider/tests/test_robot.py
zest/emailhider/tests/test_setup.py
zest/emailhider/tests/robot/test_example.robot