Metadata-Version: 1.1
Name: zest.emailhider
Version: 3.0
Summary: A simple jQuery Plone component for hiding email addresses from spammers.
Home-page: https://github.com/zestsoftware/zest.emailhider
Author: Zest Software
Author-email: info@zestsoftware.nl
License: GPL
Keywords: zestsoftware email spamprotection javascript
Platform: UNKNOWN
Classifier: Framework :: Plone
Classifier: Framework :: Plone :: 4.1
Classifier: Framework :: Plone :: 4.2
Classifier: Framework :: Plone :: 4.3
Classifier: Framework :: Plone :: 5.0
Classifier: Programming Language :: Python
Classifier: Programming Language :: Python :: 2.6
Classifier: Programming Language :: Python :: 2.7
Classifier: Topic :: Software Development :: Libraries :: Python Modules
